{
	"version": 1,
	"base_image": "codeocean/jupyterlab:3.6.1-miniconda4.12.0-python3.9-ubuntu20.04",
	"post_install": true,
	"options": {
		"registry_host_arg": true,
		"git_ask_pass": true
	},
	"installers": {
		"pip3": {
			"packages": [
				{
					"name": "aind-analysis-arch-result-access",
					"version": "0.7.2"
				},
				{
					"name": "aind-behavior-gym",
					"version": "0.4.3"
				},
				{
					"name": "aind-dynamic-foraging-models",
					"version": "0.12.0"
				},
				{
					"name": "imageio",
					"version": "2.37.0"
				},
				{
					"name": "matplotlib",
					"version": "3.9.4"
				},
				{
					"name": "numpy",
					"version": "2.0.2"
				},
				{
					"name": "pandas",
					"version": "2.3.1"
				},
				{
					"name": "pydantic",
					"version": "2.11.7"
				},
				{
					"name": "pynwb",
					"version": "3.1.1"
				},
				{
					"name": "scipy",
					"version": "1.13.1"
				},
				{
					"name": "seaborn",
					"version": "0.13.2"
				},
				{
					"name": "statsmodels",
					"version": "0.14.5"
				}
			],
			"options": {},
			"pre_install_options": {}
		}
	}
}